[{
    "RxRefill": "18634570",
    "AuthRefills": 1,
    "BillType": "Insurance",
    "CopayPaid": "Y",
    "DateFilled": "04/12/2023 00:04:01 AM",
    "DateOrdered": "04/12/2022 00:04:00 AM",
    "DatePicked": "",
    "DaysSupply": 31,
    "Diagnosis": [
    ],
    "Drug": {
     "DrugName": "METFORMIN HCL 500MG TAB",
     "ExpiryDate": "",
     "Form": "TAB",
     "LotNo": "",
     "ManufacturerName": "ACI HEALTH",
     "NDC": "71093013206",
     "SpecificProductID": 275,
     "Strength": "500",
     "StrengthUM": "MG",
     "Strong": "500MG"
    },
    "FollowupTag": "",
    "LabelPrinted": "Y",
    "Patient": {
     "Address": {
      "City": "EAST ORANGE",
      "State": "NJ",
      "StreetLine1": "73 S WALNUT ST APT 14",
      "StreetLine2": "",
      "ZipCode": "07018"
     },
     "Category": "None",
     "DOB": "11/03/1980",
     "DriverLicenseExpiry": "",
     "DriverLicenseNumber": "",
     "Email": "",
     "ExternalId": "",
     "FirstName": "APRIL",
     "Gender": "F",
     "Language": "English",
     "LastName": "WALKER",
     "MiddleInitials": "",
     "MobileNo": "9735174019",
     "PatientNo": "300",
     "Phone": "9735174019",
     "WorkPhone": ""
    },
    "PatientCopay": 0,
    "Pharmacy": {
     "Address": {
      "City": "EAST ORANGE",
      "State": "NJ",
      "StreetLine1": "358 MAIN ST",
      "StreetLine2": "",
      "ZipCode": "07018"
     },
     "FaxNo": "9732669901",
     "NABP": "3157395",
     "Name": "MIKE'S PHARMACY",
     "NPINo": "1295344927",
     "Phone": "9732669900"
    },
    "PharmVerificationDone": "N",
    "PickedUp": "N",
    "Prescriber": {
     "Address": {
      "City": "EAST ORANGE",
      "State": "NJ",
      "StreetLine1": "60 EVERGREEN PL",
      "StreetLine2": "",
      "ZipCode": "07018"
     },
     "DEARegNo": "MF2797035",
     "Email": "",
     "FaxNo": "8627042832",
     "FirstName": "VELMA",
     "LastName": "FRASIER",
     "LicenseNo": "26NJ0040060",
     "MedicaidProvNo": "",
     "MobileNo": "",
     "NPINo": "1891049490",
     "Phone": "8627042829",
     "Phone2": "",
     "PresNo": "1008"
    },
    "PrescriptionNotes": "",
    "PrimaryInsurancePaid": 26,
    "QtyDispensed": 30,
    "QtyOrdered": 30,
    "QtyRemaining": 0,
    "QueueName": "",
    "RefillNo": 0,
    "RxNo": 1863457,
    "RxOriginCode": "3",
    "RxOriginDescription": "Electronic Rx",
    "SecondaryInsurancePaid": 0,
    "Sig": "1 TABLET BY MOUTH DAILY",
    "Status": "UnBilled",
    "TertiaryInsurancePaid": 0,
    "TimePicked": "",
    "timeStamp": "Wed Apr 12 2023 13:13:47 GMT+0000 (Coordinated Universal Time)",
    "TotalRxAmount": 26
   },
   {
       "RxRefill": "1617550",
       "AuthRefills": 1,
       "BillType": "Insurance",
       "CopayPaid": "Y",
       "DateFilled": "03/29/2023 00:03:00 AM",
       "DateOrdered": "03/29/2023 00:03:00 AM",
       "DatePicked": "",
       "DaysSupply": 28,
       "Diagnosis": [
        {
         "Code": "E11.65",
         "Name": "Type 2 diabetes mellitus with hyperglycemia[E1165]",
         "Qualifier": "ICD10"
        }
       ],
       "Drug": {
        "DrugName": "BYDUREON BCISE 2MG/0.85ML INJ",
        "ExpiryDate": "",
        "Form": "INJ",
        "LotNo": "",
        "ManufacturerName": "ASTRAZENEC",
        "NDC": "00310654004",
        "SpecificProductID": 25517,
        "Strength": "2",
        "StrengthUM": "MG/0.85ML",
        "Strong": "2MG/0.85ML"
       },
       "FollowupTag": "",
       "LabelPrinted": "N",
       "Patient": {
        "Address": {
         "City": "BAYONNE",
         "State": "NJ",
         "StreetLine1": "546 KENNEDY BLV APT 4",
         "StreetLine2": "862, BROADWAY",
         "ZipCode": "07002"
        },
        "Category": "None",
        "DOB": "07/05/1969",
        "DriverLicenseExpiry": "",
        "DriverLicenseNumber": "",
        "Email": "naikrinku22@gmail.com",
        "ExternalId": "",
        "FirstName": "DIPAK",
        "Gender": "M",
        "Language": "English",
        "LastName": "NAIK",
        "MiddleInitials": "L",
        "MobileNo": "2014015229",
        "PatientNo": "3092",
        "Phone": "2012404276",
        "WorkPhone": ""
       },
       "PatientCopay": 0,
       "Pharmacy": {
        "Address": {
         "City": "BAYONNE",
         "State": "NJ",
         "StreetLine1": "557 BROADWAY",
         "StreetLine2": "",
         "ZipCode": "07002"
        },
        "FaxNo": "2014558207",
        "NABP": "3149172",
        "Name": "ULTRA CARE PHARMACY",
        "NPINo": "1215334701",
        "Phone": "2014558200"
       },
       "PharmVerificationDone": "N",
       "PickedUp": "N",
       "Prescriber": {
        "Address": {
         "City": "Bayonne",
         "State": "NJ",
         "StreetLine1": "988 BroadwaySuite 201",
         "StreetLine2": "",
         "ZipCode": "07002"
        },
        "DEARegNo": "FS0303622",
        "Email": "",
        "FaxNo": "2013396333",
        "FirstName": "Emily",
        "LastName": "Silverman",
        "LicenseNo": "",
        "MedicaidProvNo": "",
        "MobileNo": "",
        "NPINo": "1346695467",
        "Phone": "9735466844",
        "Phone2": "2013396111",
        "PresNo": "2137"
       },
       "PrescriptionNotes": "",
       "PrimaryInsurancePaid": 1496.03,
       "QtyDispensed": 3.4,
       "QtyOrdered": 10.2,
       "QtyRemaining": 6.8,
       "QueueName": "",
       "RefillNo": 0,
       "RxNo": 161755,
       "RxOriginCode": "3",
       "RxOriginDescription": "Electronic Rx",
       "SecondaryInsurancePaid": 0,
       "Sig": "INJECT 0.85 ML (2 MG TOTAL) UNDER THE SKIN 1 (ONE) TIME PER WEEK.",
       "Status": "Filed",
       "TertiaryInsurancePaid": 0,
       "TimePicked": "",
       "timeStamp": "Sat May 27 2023 18:11:02 GMT+0000 (Coordinated Universal Time)",
       "TotalRxAmount": 1496.03
      },
      {
       "RxRefill": "1024360",
       "AuthRefills": 0,
       "BillType": "Insurance",
       "CopayPaid": "Y",
       "DateFilled": "02/15/2023 00:02:00 AM",
       "DateOrdered": "02/15/2023 00:02:00 AM",
       "DatePicked": "",
       "DaysSupply": 30,
       "Diagnosis": [
        {
         "Code": "G89.4",
         "Name": "Chronic pain syndrome[G894]",
         "Qualifier": "ICD10"
        }
       ],
       "Drug": {
        "DrugName": "morphine SULFATE ER 30MG TAB",
        "ExpiryDate": "",
        "Form": "TAB",
        "LotNo": "",
        "ManufacturerName": "RHODES PHA",
        "NDC": "42858080201",
        "SpecificProductID": 801,
        "Strength": "30",
        "StrengthUM": "MG",
        "Strong": "30MG"
       },
       "FollowupTag": "",
       "LabelPrinted": "N",
       "Patient": {
        "Address": {
         "City": "HAINESPORT",
         "State": "NJ",
         "StreetLine1": "2516 FOSTERTOWN RD",
         "StreetLine2": "",
         "ZipCode": "08036"
        },
        "Category": "None",
        "DOB": "08/24/1955",
        "DriverLicenseExpiry": "",
        "DriverLicenseNumber": "",
        "Email": "",
        "ExternalId": "",
        "FirstName": "SALLI",
        "Gender": "F",
        "Language": "English",
        "LastName": "GREINER",
        "MiddleInitials": "",
        "MobileNo": "",
        "PatientNo": "2923",
        "Phone": "6092845858",
        "WorkPhone": ""
       },
       "PatientCopay": 35.47,
       "Pharmacy": {
        "Address": {
         "City": "Lumberton",
         "State": "NJ",
         "StreetLine1": "1613 Rt 38 Unit # 5",
         "StreetLine2": "",
         "ZipCode": "08048"
        },
        "FaxNo": "6099144891",
        "NABP": "3152383",
        "Name": "Mt. Holly Pharmacy",
        "NPINo": "1609328111",
        "Phone": "6099144890"
       },
       "PharmVerificationDone": "N",
       "PickedUp": "N",
       "Prescriber": {
        "Address": {
         "City": "HAINESPORT",
         "State": "NJ",
         "StreetLine1": "404 CREEK CROSSING BLVD",
         "StreetLine2": "",
         "ZipCode": "08036"
        },
        "DEARegNo": "MF4724161",
        "Email": "",
        "FaxNo": "6092886078",
        "FirstName": "DEBRA",
        "LastName": "FENDERSON-IVERY",
        "LicenseNo": "26NS00743900",
        "MedicaidProvNo": "",
        "MobileNo": "",
        "NPINo": "1902306624",
        "Phone": "6098453988",
        "Phone2": "1103",
        "PresNo": "804"
       },
       "PrescriptionNotes": "",
       "PrimaryInsurancePaid": 0,
       "QtyDispensed": 60,
       "QtyOrdered": 60,
       "QtyRemaining": 0,
       "QueueName": "",
       "RefillNo": 0,
       "RxNo": 102436,
       "RxOriginCode": "3",
       "RxOriginDescription": "Electronic Rx",
       "SecondaryInsurancePaid": 0,
       "Sig": "1 TABLET ORALLY EVERY 12 HRS 30 DAYS",
       "Status": "UnBilled",
       "TertiaryInsurancePaid": 0,
       "TimePicked": "",
       "timeStamp": "Mon Jun 05 2023 01:24:59 GMT+0000 (Coordinated Universal Time)",
       "TotalRxAmount": 195.32
      },
      {
       "RxRefill": "1656190",
       "AuthRefills": 1,
       "BillType": "Insurance",
       "CopayPaid": "Y",
       "DateFilled": "06/30/2023 00:06:00 AM",
       "DateOrdered": "06/29/2023 00:06:00 AM",
       "DatePicked": "",
       "DaysSupply": 90,
       "Diagnosis": [
       ],
       "Drug": {
        "DrugName": "METFORMIN HCL 500MG TAB",
        "ExpiryDate": "",
        "Form": "TAB",
        "LotNo": "",
        "ManufacturerName": "SCIEGEN PH",
        "NDC": "50228010510",
        "SpecificProductID": 275,
        "Strength": "",
        "StrengthUM": "",
        "Strong": "500MG"
       },
       "FollowupTag": "",
       "LabelPrinted": "Y",
       "Patient": {
        "Address": {
         "City": "BAYONNE",
         "State": "NJ",
         "StreetLine1": "1034 KENNEDY BLVD, APT 1A",
         "StreetLine2": "",
         "ZipCode": "07002"
        },
        "Category": "None",
        "DOB": "06/09/1953",
        "DriverLicenseExpiry": "",
        "DriverLicenseNumber": "",
        "Email": "",
        "ExternalId": "",
        "FirstName": "AHTASHAM",
        "Gender": "M",
        "Language": "English",
        "LastName": "AHMAD",
        "MiddleInitials": "",
        "MobileNo": "6467171161",
        "PatientNo": "1283",
        "Phone": "2124709409",
        "WorkPhone": ""
       },
       "PatientCopay": 0,
       "Pharmacy": {
        "Address": {
         "City": "BAYONNE",
         "State": "NJ",
         "StreetLine1": "557 BROADWAY",
         "StreetLine2": "",
         "ZipCode": "07002"
        },
        "FaxNo": "2014558207",
        "NABP": "3149172",
        "Name": "ULTRA CARE PHARMACY",
        "NPINo": "1215334701",
        "Phone": "2014558200"
       },
       "PharmVerificationDone": "N",
       "PickedUp": "N",
       "Prescriber": {
        "Address": {
         "City": "BAYONNE",
         "State": "NJ",
         "StreetLine1": "16  EAST  29th  ST",
         "StreetLine2": "",
         "ZipCode": "07002"
        },
        "DEARegNo": "BA7113549",
        "Email": "miantaziz@yahoo.com",
        "FaxNo": "2013392557",
        "FirstName": "Shahnaz",
        "LastName": "Akhtar",
        "LicenseNo": "25MA07176700",
        "MedicaidProvNo": "",
        "MobileNo": "",
        "NPINo": "1619912102",
        "Phone": "2013391685",
        "Phone2": "2013392584",
        "PresNo": "90"
       },
       "PrescriptionNotes": "",
       "PrimaryInsurancePaid": 240.08,
       "QtyDispensed": 180,
       "QtyOrdered": 180,
       "QtyRemaining": 0,
       "QueueName": "",
       "RefillNo": 0,
       "RxNo": 165619,
       "RxOriginCode": "4",
       "RxOriginDescription": "Facsimile Rx",
       "SecondaryInsurancePaid": 0,
       "Sig": "1T PO BID",
       "Status": "UnBilled",
       "TertiaryInsurancePaid": 0,
       "TimePicked": "",
       "timeStamp": "Fri Jun 30 2023 16:55:08 GMT+0000 (Coordinated Universal Time)",
       "TotalRxAmount": 240.08
   }]